[
  {
    "name": "Mikhaylovgrad"
  },
  {
    "name": "Blagoevgrad"
  },
  {
    "name": "Burgas"
  },
  {
    "name": "Dobrich"
  },
  {
    "name": "Gabrovo"
  },
  {
    "name": "Grad Sofiya"
  },
  {
    "name": "Khaskovo"
  },
  {
    "name": "Kurdzhali"
  },
  {
    "name": "Kyustendil"
  },
  {
    "name": "Lovech"
  },
  {
    "name": "Montana"
  },
  {
    "name": "Pazardzhik"
  },
  {
    "name": "Pernik"
  },
  {
    "name": "Pleven"
  },
  {
    "name": "Plovdiv"
  },
  {
    "name": "Razgrad"
  },
  {
    "name": "Ruse"
  },
  {
    "name": "Shumen"
  },
  {
    "name": "Silistra"
  },
  {
    "name": "Sliven"
  },
  {
    "name": "Smolyan"
  },
  {
    "name": "Sofiya"
  },
  {
    "name": "Stara Zagora"
  },
  {
    "name": "Turgovishte"
  },
  {
    "name": "Varna"
  },
  {
    "name": "Veliko Turnovo"
  },
  {
    "name": "Vidin"
  },
  {
    "name": "Vratsa"
  },
  {
    "name": "Yambol"
  }
]